<?xml version="1.0" encoding="UTF-8" standalone="no"?>
<compiereTrl baseLanguage="en_US" language="es_ES" table="AD_FIELD" version="">
  <row id="01AD50AC5B6B498BBF27CE93423B9DDF" trl="Y">
    <value column="Name" isTrl="Y" original="Expected Amount">Importe esperado</value>
    <value column="Description" isTrl="N" original=""/>
    <value column="Help" isTrl="N" original=""/>
  </row>
  <row id="0A23152718D54E99B941D9AA1BF33734" trl="Y">
    <value column="Name" isTrl="Y" original="Invoice No.">Núm. factura</value>
    <value column="Description" isTrl="Y" original="An often automatically generated identifier for all documents.">Identificador de documentos que puede generarse automáticamente.</value>
    <value column="Help" isTrl="Y" original="The document number is usually automatically generated by the system and determined by the document type of the document. If the document is not saved, the preliminary number is displayed in &quot;&lt;&gt;&quot;. If the document type of your document has no automatic document sequence defined, the field will be empty when creating a new document. This is for documents which usually have an external number (like vendor invoice).  If you leave the field empty, the system will generate a document number for you. The document sequence used for this fallback number is defined in the &quot;Document Sequence&quot; window with the name &quot;DocumentNo_&lt;TableName&gt;&quot;, where TableName is the actual name of the table inside the database (e.g. C_Order).">El número del documento suele ser generado automáticamente por el sistema y está determinado por el tipo de documento del propio documento. Si no se guarda el documento, el número preliminar se muestra con "&amp;amp;lt;&amp;amp;gt;". Si el tipo de documento no tiene definido la generación automática del número éste quedará vacío al crear el nuevo documento. Puede ocurrir para aquellos documentos que tienen números externos(factura de venta). Si se deja vacío el sistema le generará un número. La secuencia de números utilizada en los documentos está definida en la ventana "Mantenimiento de la secuencia" con el nombre "Númerodocumento_NombreTabla", donde el nombre de la tabla es en nombre actual de la misma (p.ej C_Orde).</value>
  </row>
  <row id="10F24EF51B8149EC9F9E86CE9BE97BD2" trl="Y">
    <value column="Name" isTrl="Y" original="Sender">Remitente</value>
    <value column="Description" isTrl="Y" original="Anyone who takes part in daily business operations by acting as a customer, employee, etc.">Persona que participa en operaciones diarias de negocios, como cliente, empleado, etc.</value>
    <value column="Help" isTrl="Y" original="A Business Partner is anyone with whom you transact.  This can include a customer, vendor, employee or any combination of these.">Un tercero es aquel con el que se realiza alguna transacción. Esto incluye clientes, proveedores, empleados o cualquier combinación de ellos.</value>
  </row>
  <row id="110FB2A04E69473784A8478D0BD8B3FB" trl="Y">
    <value column="Name" isTrl="Y" original="Add Payment">Añadir pago</value>
    <value column="Description" isTrl="Y" original="Add Payment From Journal Line">Añadir pago desde línea del diario</value>
    <value column="Help" isTrl="Y" original="Process to add new Payments from the G/L Journal Lines.">Procesar para añadir nuevos pagos desde las líneas de asientos contables.</value>
  </row>
  <row id="2224A72A74ED41E8AB02F64BB8C3637E" trl="Y">
    <value column="Name" isTrl="Y" original="Original Due Date">Fecha venicimiento original</value>
    <value column="Description" isTrl="Y" original="Due date for the payment plan as per contract">Fecha vencimiento del plan de pago por contrato</value>
    <value column="Help" isTrl="Y" original="Due date for the payment plan as per contract">Fecha vencimiento del plan de pago por contrato</value>
  </row>
  <row id="3287F4B82C964ADAA98CF144A21719E2" trl="Y">
    <value column="Name" isTrl="Y" original="Supplier Reference">Referencia del Proveedor</value>
    <value column="Description" isTrl="Y" original="A reference or document order number as listed in business partner application.">Una referencia o número de documento del tercero</value>
    <value column="Help" isTrl="Y" original="This can be used to input a reference for this specific transaction. For example, a Purchase Order number can be input on a Sales Order for easier reference.">Se puede utilizar para insertar una referencia para esta transacción. Por ejemplo, un número de pedido de compra se puede insertar en un pedido de venta para referenciar mejor.</value>
  </row>
  <row id="37DF9510E7134AEC8CF265DB7C208207" trl="Y">
    <value column="Name" isTrl="Y" original="Business Partner">Tercero</value>
    <value column="Description" isTrl="Y" original="Business Partner Name">Nombre del Tercero</value>
    <value column="Help" isTrl="Y" original="Business Partner Name">Nombre del Tercero</value>
  </row>
  <row id="58D6982C3BD046EB831A9D61095B763F" trl="Y">
    <value column="Name" isTrl="Y" original="Transaction Description">Descripción de la Transacción</value>
    <value column="Description" isTrl="Y" original="A space to write additional related information.">Un espacio para escribir información relacionada adicional.</value>
    <value column="Help" isTrl="Y" original="A description is limited to 255 characters.">La descripción está limitada a 255 caracteres</value>
  </row>
  <row id="75E24F44C2F34699A21222ACA723244E" trl="Y">
    <value column="Name" isTrl="Y" original="bslUpdated">lebActualizada</value>
    <value column="Description" isTrl="Y" original="The date that this record was last updated">Fecha en la que el registro se actualizó por última vez</value>
    <value column="Help" isTrl="Y" original="The Updated field indicates the date that this record was updated.">La Fecha de Actualización indica la fecha en la que el registro fue actualizado por última vez.</value>
  </row>
  <row id="7985E4F3C77F40DEB85E9BBDBACCD28C" trl="Y">
    <value column="Name" isTrl="Y" original="Business Partner Name">Nombre del Tercero</value>
    <value column="Description" isTrl="Y" original="Business Partner Name">Nombre del Tercero</value>
    <value column="Help" isTrl="Y" original="Business Partner Name">Nombre del Tercero</value>
  </row>
  <row id="84A66F76B075429F989283C5F074367E" trl="Y">
    <value column="Name" isTrl="Y" original="Invoice No.">Núm. factura</value>
    <value column="Description" isTrl="Y" original="An often automatically generated identifier for all documents.">Identificador de documentos que puede generarse automáticamente.</value>
    <value column="Help" isTrl="Y" original="The document number is usually automatically generated by the system and determined by the document type of the document. If the document is not saved, the preliminary number is displayed in &quot;&lt;&gt;&quot;. If the document type of your document has no automatic document sequence defined, the field will be empty when creating a new document. This is for documents which usually have an external number (like vendor invoice).  If you leave the field empty, the system will generate a document number for you. The document sequence used for this fallback number is defined in the &quot;Document Sequence&quot; window with the name &quot;DocumentNo_&lt;TableName&gt;&quot;, where TableName is the actual name of the table inside the database (e.g. C_Order).">El número del documento suele ser generado automáticamente por el sistema y está determinado por el tipo de documento del propio documento. Si no se guarda el documento, el número preliminar se muestra con "&amp;amp;lt;&amp;amp;gt;". Si el tipo de documento no tiene definido la generación automática del número éste quedará vacío al crear el nuevo documento. Puede ocurrir para aquellos documentos que tienen números externos(factura de venta). Si se deja vacío el sistema le generará un número. La secuencia de números utilizada en los documentos está definida en la ventana "Mantenimiento de la secuencia" con el nombre "Númerodocumento_NombreTabla", donde el nombre de la tabla es en nombre actual de la misma (p.ej C_Orde).</value>
  </row>
  <row id="9E4ED210DB344E538CA6921C0111E8DD" trl="Y">
    <value column="Name" isTrl="Y" original="Funds Transfer Enabled">Habilitada para Transferencia de Fondos</value>
    <value column="Description" isTrl="Y" original="Funds Transfer Enabled flag is used to show/hide funds transfer button process.">Habilitada para Transferencia de Fondos se utiliza para mostrar/ocultar la funcionalidad de Transferencia de Fondos.</value>
    <value column="Help" isTrl="Y" original="Funds Transfer Enabled flag is used to show/hide funds transfer button process.">Habilitada para Transferencia de Fondos se utiliza para mostrar/ocultar la funcionalidad de Transferencia de Fondos.</value>
  </row>
  <row id="A401C01A407B465091839A0700362D45" trl="Y">
    <value column="Name" isTrl="Y" original="Name">Nombre</value>
    <value column="Description" isTrl="Y" original="Description of the accounting entry">Descripción de la entrada contable</value>
    <value column="Help" isTrl="Y" original="Description of the accounting entry">Descripción del asiento contable</value>
  </row>
  <row id="ADC8DA402DA2432B94DFC87A8CD0930A" trl="Y">
    <value column="Name" isTrl="Y" original="Match">Conciliar</value>
    <value column="Description" isTrl="N" original=""/>
    <value column="Help" isTrl="N" original=""/>
  </row>
  <row id="B41A028362C548F8949B314C44672BEC" trl="Y">
    <value column="Name" isTrl="Y" original="Received Amount">Importe recibido</value>
    <value column="Description" isTrl="N" original=""/>
    <value column="Help" isTrl="N" original=""/>
  </row>
  <row id="B62C63760FA84CCDB4E6B056A7AA5EBE" trl="Y">
    <value column="Name" isTrl="Y" original="Received Amount">Importe recibido</value>
    <value column="Description" isTrl="N" original=""/>
    <value column="Help" isTrl="N" original=""/>
  </row>
  <row id="E1C896D9A8104AC3B6A0B995683122D7" trl="Y">
    <value column="Name" isTrl="Y" original="Transaction Amount">Importe Transacción</value>
    <value column="Description" isTrl="Y" original="A monetary total.">Importe total.</value>
    <value column="Help" isTrl="Y" original="The Amount indicates the amount for this document line.">Indica el importe para este documento. </value>
  </row>
  <row id="E7DEB6F4F8894B7B8A8D143782359FEF" trl="Y">
    <value column="Name" isTrl="Y" original="Expected Amount">Importe esperado</value>
    <value column="Description" isTrl="N" original=""/>
    <value column="Help" isTrl="N" original=""/>
  </row>
  <row id="EDA2BCAC69ED4168A72632F257E79568" trl="Y">
    <value column="Name" isTrl="N" original="Debit">Debit</value>
    <value column="Description" isTrl="Y" original="The amount debited to an account, converted to the organization default currency.">El importe en el debe de una cuenta, convertida a la moneda por defecto de la organización.</value>
    <value column="Help" isTrl="Y" original="The Account Debit Amount indicates the transaction amount converted to this organization's accounting currency">La Cuenta de Importe Débito indica el importe de la transacción convertida a esta moneda de la organización</value>
  </row>
</compiereTrl>
