<?xml version="1.0" encoding="UTF-8"?><ob:Openbravo xmlns:ob="http://www.openbravo.com" xmlns:xsi="http://www.w3.org/2001/XMLSchema-instance">
  <PricingPriceList id="B7D1B99783474B3A85FEB736D29C9724" identifier="VENTA-DOLARES">
    <id>B7D1B99783474B3A85FEB736D29C9724</id>
    <active>true</active>
    <name>VENTA-DOLARES</name>
    <description>VENTA-DOLARES</description>
    <basePricelist xsi:nil="true"/>
    <priceIncludesTax>false</priceIncludesTax>
    <salesPriceList>true</salesPriceList>
    <default>true</default>
    <currency id="100" entity-name="Currency" identifier="USD"/>
    <enforcePriceLimit>false</enforcePriceLimit>
    <costBasedPriceList>false</costBasedPriceList>
  </PricingPriceList>
  <PricingPriceList id="BE41AA2D48A7481EA3DC7FE99F2F1407" identifier="COMPRA-DOLARES">
    <id>BE41AA2D48A7481EA3DC7FE99F2F1407</id>
    <active>true</active>
    <name>COMPRA-DOLARES</name>
    <description>COMPRA-DOLARES</description>
    <basePricelist xsi:nil="true"/>
    <priceIncludesTax>false</priceIncludesTax>
    <salesPriceList>false</salesPriceList>
    <default>false</default>
    <currency id="100" entity-name="Currency" identifier="USD"/>
    <enforcePriceLimit>false</enforcePriceLimit>
    <costBasedPriceList>false</costBasedPriceList>
  </PricingPriceList>
</ob:Openbravo>
